DESCRIPTION.rst
LICENSE
MANIFEST.in
README.md
setup.py
examples/__init__.py
examples/crc32/__init__.py
examples/crc32/crc32.py
examples/dff/dff.py
examples/dff/dff1.py
examples/eth_1g_mac/__init__.py
examples/eth_1g_mac/eth_1g_mac.py
examples/johnson/johnson.py
sydpy/__init__.py
sydpy/_channel.py
sydpy/_component.py
sydpy/_configurator.py
sydpy/_delay.py
sydpy/_event.py
sydpy/_module.py
sydpy/_process.py
sydpy/_signal.py
sydpy/_simulator.py
sydpy.egg-info/PKG-INFO
sydpy.egg-info/SOURCES.txt
sydpy.egg-info/dependency_links.txt
sydpy.egg-info/requires.txt
sydpy.egg-info/top_level.txt
sydpy/_util/__init__.py
sydpy/_util/_injector.py
sydpy/_util/_util.py
sydpy/_util/decorator.py
sydpy/extens/__init__.py
sydpy/extens/coverage.py
sydpy/extens/profiler.py
sydpy/extens/simprog.py
sydpy/extens/tracing.py
sydpy/intfs/__init__.py
sydpy/intfs/_intf.py
sydpy/intfs/seq.py
sydpy/intfs/sig.py
sydpy/intfs/strm.py
sydpy/intfs/tlm.py
sydpy/procs/__init__.py
sydpy/procs/clk.py
sydpy/rnd/__init__.py
sydpy/rnd/rnd.py
sydpy/types/__init__.py
sydpy/types/_type_base.py
sydpy/types/array.py
sydpy/types/bit.py
sydpy/types/enum.py
sydpy/types/struct.py
sydpy/types/vector.py
sydpy/verif/__init__.py
sydpy/verif/basic_rnd_seq.py
sydpy/verif/basic_seq.py
sydpy/verif/scoreboard.py
sydpy/verif/sequencer.py
sydpy/verif/unittest.py
tests/__init__.py
tests/test_data_types.py
tests/test_examples.py
tests/test_symexp.py