Metadata-Version: 1.1
Name: sydpy
Version: 0.0.1
Summary: System Design in Python
Home-page: https://github.com/bogdanvuk/sydpy
Author: Bogdan Vukobratovic
Author-email: bogdan.vukobratovic@gmail.com
License: LGPL
Download-URL: https://github.com/bogdanvuk/sydpy/tarball/0.0.1
Keywords: System Design Python Simulator HDL ASIC FPGA verification TLM
Platform: UNKNOWN
Classifier: Development Status :: 3 - Alpha
Classifier: Intended Audience :: Developers
Classifier: Topic :: Scientific/Engineering :: Electronic Design Automation (EDA)
Classifier: License :: OSI Approved :: GNU Library or Lesser General Public License (LGPL)
Classifier: Programming Language :: Python :: 3.3
Classifier: Programming Language :: Python :: 3.4
